schematec/__init__.py
schematec/abc.py
schematec/converters.py
schematec/exc.py
schematec/schema.py
schematec/validators.py
schematec-0.5.2.dist-info/DESCRIPTION.rst
schematec-0.5.2.dist-info/METADATA
schematec-0.5.2.dist-info/metadata.json
schematec-0.5.2.dist-info/RECORD
schematec-0.5.2.dist-info/top_level.txt
schematec-0.5.2.dist-info/WHEEL
